torchdtw/_C.pyd
torchdtw/__init__.py
torchdtw/py.typed
torchdtw/csrc/dtw.cpp
torchdtw/csrc/cuda/dtw.cu
torchdtw-0.1.0.dist-info/METADATA
torchdtw-0.1.0.dist-info/WHEEL
torchdtw-0.1.0.dist-info/top_level.txt
torchdtw-0.1.0.dist-info/RECORD
