Metadata-Version: 2.4
Name: torchdtw
Version: 0.1.0
Summary: PyTorch DTW C++ extension
Author: Maxime Poli
Author-email: CoML <dev@cognitive-ml.fr>
License-Expression: MIT
Keywords: machine learning
Classifier: Development Status :: 4 - Beta
Classifier: Intended Audience :: Science/Research
Classifier: Operating System :: OS Independent
Classifier: Programming Language :: C++
Classifier: Programming Language :: Python :: 3 :: Only
Classifier: Programming Language :: Python :: 3.12
Classifier: Programming Language :: Python :: 3.13
Classifier: Programming Language :: Python :: 3.14
Classifier: Topic :: Scientific/Engineering
Classifier: Topic :: Scientific/Engineering :: Artificial Intelligence
Requires-Python: >=3.12
Requires-Dist: torch>=2.10.0
Provides-Extra: test
Requires-Dist: hypothesis>=6.142.5; extra == "test"
Requires-Dist: pytest>=8.4.2; extra == "test"
